__init__.py
gswpy.py
gswpy-0.0.1.dist-info/LICENSE
gswpy-0.0.1.dist-info/METADATA
gswpy-0.0.1.dist-info/WHEEL
gswpy-0.0.1.dist-info/top_level.txt
gswpy-0.0.1.dist-info/RECORD
